topsis/__init__.py
topsis/topsis.py
Topsis_JiteshSilhi_101903797-5.0.0.dist-info/LICENSE
Topsis_JiteshSilhi_101903797-5.0.0.dist-info/METADATA
Topsis_JiteshSilhi_101903797-5.0.0.dist-info/WHEEL
Topsis_JiteshSilhi_101903797-5.0.0.dist-info/entry_points.txt
Topsis_JiteshSilhi_101903797-5.0.0.dist-info/top_level.txt
Topsis_JiteshSilhi_101903797-5.0.0.dist-info/RECORD
